minform-0.2.1.dist-info/DESCRIPTION.rst
minform-0.2.1.dist-info/METADATA
minform-0.2.1.dist-info/top_level.txt
minform-0.2.1.dist-info/WHEEL
minform-0.2.1.dist-info/RECORD
minform-0.2.1.dist-info/metadata.json
minform/compound.py
minform/basic.py
minform/core.py
minform/__init__.py
