Metadata-Version: 2.0
Name: minform
Version: 0.2.1
Summary: WTForms/struct integration to validate and serialize to packed buffers of binary data.
Home-page: https://github.com/daviddonna/minform
Author: David Donna
Author-email: davidadonna@gmail.com
License: ISCL
Keywords: minform wtforms struct binary
Platform: UNKNOWN
Classifier: Development Status :: 4 - Beta
Classifier: Intended Audience :: Developers
Classifier: License :: OSI Approved :: ISC License (ISCL)
Classifier: Natural Language :: English
Classifier: Programming Language :: Python :: 2
Classifier: Programming Language :: Python :: 2.6
Classifier: Programming Language :: Python :: 2.7
Classifier: Programming Language :: Python :: 3
Classifier: Programming Language :: Python :: 3.3
Classifier: Programming Language :: Python :: 3.4
Requires-Dist: WTForms (>=2.0.2)
Requires-Dist: six (>=1.9.0)
